[
  {
    "product_id": "1731253726908089798",
    "title": "5 X CERAMIDE MILKY CLEANSER 100ml facial",
    "sale_price_rm": "39",
    "original_price_rm": "49",
    "discount_percentage": "20%",
    "savings_amount": "Saving RM10.00",
    "units_sold": 50875,
    "rating_score": 4.9,
    "review_count": 12176,
    "shop_name": "NFG BEAUTYCARE",
    "shop_id": "7494691249571662278",
    "free_shipping": false,
    "product_url": "https://shop.tiktok.com/my/pdp/pencuci-muka-ceramide-lembut-100ml-untuk-kulit-kering-dan-sensitif-kelembapan-72-jam-haruman-spa-men/1731253726908089798",
    "image_url": "https://p16-oec-sg.ibyteimg.com/tos-alisg-i-aphluv4xwc-sg/468369d316254abcb7d8ffb385aac5fb~tplv-aphluv4xwc-crop-webp:1200:1200.webp?dr=15592&t=555f072d&ps=933b5bde&shp=8dbd94bf&shcp=d741f1be&idc=my&from=2378011839",
    "source": "WIRETAP"
  },
  {
    "product_id": "1729621600902874173",
    "title": "TUDUNG SARUNG SPORTS HIJAB by Dexxe",
    "sale_price_rm": "23.88",
    "original_price_rm": "31.9",
    "discount_percentage": "25%",
    "savings_amount": "Saving RM8.02",
    "units_sold": 81652,
    "rating_score": 4.8,
    "review_count": 11952,
    "shop_name": "ABANG JERSI",
    "shop_id": "7495125082463373373",
    "free_shipping": false,
    "product_url": "https://shop.tiktok.com/my/pdp/tudung-sarung-netball-dryfit-ironless-sesuai-untuk-sukan/1729621600902874173",
    "image_url": "https://p16-oec-sg.ibyteimg.com/tos-alisg-i-aphluv4xwc-sg/3d465d2ec76a49afaf70ed6dfb45aed7~tplv-aphluv4xwc-crop-webp:1200:1200.webp?dr=15592&t=555f072d&ps=933b5bde&shp=8dbd94bf&shcp=d741f1be&idc=my&from=2378011839",
    "source": "WIRETAP"
  },
  {
    "product_id": "1731066307045917728",
    "title": "SKINTIFIC 5X Ceramide Barrier Moisture Cream Ceramide Moisturizer Repair Skin Barrier Moisturiser Bigger Size-80g Hyaluronic Penjagaan Kulit",
    "sale_price_rm": "69",
    "original_price_rm": "99",
    "discount_percentage": "30%",
    "savings_amount": "Saving RM30.00",
    "units_sold": 28075,
    "rating_score": 4.9,
    "review_count": 5169,
    "shop_name": "Skintific.my",
    "shop_id": "7496066244267640864",
    "free_shipping": false,
    "product_url": "https://shop.tiktok.com/my/pdp/krim-pelembap-skintific-5x-ceramide-80g-baiki-barrier-kulit-tidak-menggelembung-sesuai-semua-jenis-k/1731066307045917728",
    "image_url": "https://p16-oec-sg.ibyteimg.com/tos-alisg-i-aphluv4xwc-sg/10a0bde62d8e40698bb5c5333c4726e3~tplv-aphluv4xwc-crop-webp:1200:1200.webp?dr=15592&t=555f072d&ps=933b5bde&shp=8dbd94bf&shcp=d741f1be&idc=my&from=2378011839",
    "source": "WIRETAP"
  },
  {
    "product_id": "1729620123751385785",
    "title": "(VITRI SHOP)Baju tidur korean style cotton polyster premium short sleve Pajamas Sleepwear, baju tidur lengan pendek seluar panjang,lengan panjang seluar panjang",
    "sale_price_rm": "19.99",
    "original_price_rm": "59.99",
    "discount_percentage": "67%",
    "savings_amount": "Saving RM40.00",
    "units_sold": 77128,
    "rating_score": 4.9,
    "review_count": 18484,
    "shop_name": "Vittri shop",
    "shop_id": "7494537247219288761",
    "free_shipping": false,
    "product_url": "https://shop.tiktok.com/my/pdp/baju-tidur-korean-style-cotton-silk-lengan-pendek-panjang/1729620123751385785",
    "image_url": "https://p16-oec-sg.ibyteimg.com/tos-alisg-i-aphluv4xwc-sg/badfdd59d66348558d92c7a651f01eb5~tplv-aphluv4xwc-crop-webp:1254:1254.webp?dr=15592&t=555f072d&ps=933b5bde&shp=8dbd94bf&shcp=d741f1be&idc=my&from=2378011839",
    "source": "WIRETAP"
  },
  {
    "product_id": "1732385261157517145",
    "title": "VESSO Blossom Breeze Tumbler 1000ml – Premium Stainless Steel Insulated Water Bottle, Large Capacity Hot & Cold Flask, Leakproof Portable Travel Tumbler, Eco-Friendly Reusable Drink Bottle",
    "sale_price_rm": "21.8",
    "original_price_rm": "57.9",
    "discount_percentage": "62%",
    "savings_amount": "Saving RM36.10",
    "units_sold": 53500,
    "rating_score": 4.9,
    "review_count": 11473,
    "shop_name": "VESSO Malaysia",
    "shop_id": "7496212307664276313",
    "free_shipping": false,
    "product_url": "https://shop.tiktok.com/my/pdp/vesso-blossom-breeze-tumbler-1000ml-botol-air-stainless-steel-kapasiti-besar-kalis-kebocoran-memelih/1732385261157517145",
    "image_url": "https://p16-oec-sg.ibyteimg.com/tos-alisg-i-aphluv4xwc-sg/506f18ac07674c5ea6e7f4c4170ba63f~tplv-aphluv4xwc-crop-webp:1080:1080.webp?dr=15592&t=555f072d&ps=933b5bde&shp=8dbd94bf&shcp=d741f1be&idc=my&from=2378011839",
    "source": "WIRETAP"
  },
  {
    "product_id": "1731945740189271571",
    "title": "Makarizo Barber Daily Acne Care Oil Control Face Wash 100ml | Pencuci Muka Kawalan Minyak & Jerawat | Lembut & pH Rendah | embersih pori | Kawal minyak | Lawan jerawat | Sesuai untuk kulit sensitif",
    "sale_price_rm": "17.9",
    "original_price_rm": "0.00",
    "discount_percentage": "",
    "savings_amount": "",
    "units_sold": 10439,
    "rating_score": 4.8,
    "review_count": 1748,
    "shop_name": "Barber Daily MY",
    "shop_id": "7496188055460284947",
    "free_shipping": false,
    "product_url": "https://shop.tiktok.com/my/pdp/pencuci-muka-kawalan-minyak-jerawat-formula-lembut/1731945740189271571",
    "image_url": "https://p16-oec-sg.ibyteimg.com/tos-alisg-i-aphluv4xwc-sg/b55e5ee783cb4c2b97e85069e5b2a40b~tplv-aphluv4xwc-crop-webp:1000:1000.webp?dr=15592&t=555f072d&ps=933b5bde&shp=8dbd94bf&shcp=d741f1be&idc=my&from=2378011839",
    "source": "WIRETAP"
  },
  {
    "product_id": "1735027414912108056",
    "title": "Kain lap gentian kayu, tak perlu pencuci, bilas air je terus bersih, sesuai untuk dapur, kereta & motosikal.",
    "sale_price_rm": "7.33",
    "original_price_rm": "8.99",
    "discount_percentage": "18%",
    "savings_amount": "Saving RM1.66",
    "units_sold": 6748,
    "rating_score": 4.7,
    "review_count": 1073,
    "shop_name": "EASTJAY-HOMECARE",
    "shop_id": "7494513451230725656",
    "free_shipping": false,
    "product_url": "https://shop.tiktok.com/my/pdp/1735027414912108056",
    "image_url": "https://p16-oec-sg.ibyteimg.com/tos-alisg-i-aphluv4xwc-sg/69bb1ac6bc804926820051c3e73e2424~tplv-aphluv4xwc-crop-webp:800:800.webp?dr=15592&t=555f072d&ps=933b5bde&shp=8dbd94bf&shcp=d741f1be&idc=my&from=2378011839",
    "source": "WIRETAP"
  },
  {
    "product_id": "1735066422652995295",
    "title": "【SiliosCare】 hidrokoloid, untuk jerawat,  saiz dan bentuk DIY,  1m acne scars hydrocolloid roll pimple patch",
    "sale_price_rm": "15.9",
    "original_price_rm": "38",
    "discount_percentage": "58%",
    "savings_amount": "Saving RM22.10",
    "units_sold": 4059,
    "rating_score": 4.8,
    "review_count": 617,
    "shop_name": "SiliosCare.MY",
    "shop_id": "7494547630369375967",
    "free_shipping": false,
    "product_url": "https://shop.tiktok.com/my/pdp/1735066422652995295",
    "image_url": "https://p16-oec-sg.ibyteimg.com/tos-alisg-i-aphluv4xwc-sg/c83bfecd6352494d9f71c165dde71204~tplv-aphluv4xwc-crop-webp:1254:1254.webp?dr=15592&t=555f072d&ps=933b5bde&shp=8dbd94bf&shcp=d741f1be&idc=my&from=2378011839",
    "source": "WIRETAP"
  },
  {
    "product_id": "1732939269882217710",
    "title": "【100% Authentic】Jam Tangan Lelaki LIBIS Jenama Asal Siri Penjelajah Mewah Kalis Air dengan Paparan Malam dan Kalendar Pilihan Hadiah Terbaik untuk Lelaki Watches Jam tangan lelaki kalis air bersinar dengan paparan bercahaya dan kalendar",
    "sale_price_rm": "47.5",
    "original_price_rm": "449",
    "discount_percentage": "89%",
    "savings_amount": "Saving RM401.50",
    "units_sold": 10839,
    "rating_score": 4.8,
    "review_count": 2182,
    "shop_name": "MUKUO.LIBIS",
    "shop_id": "7496265493979957486",
    "free_shipping": false,
    "product_url": "https://shop.tiktok.com/my/pdp/jam-tangan-lelaki-libis-kalis-air-bersinar-paparan-malam-kalendar/1732939269882217710",
    "image_url": "https://p16-oec-sg.ibyteimg.com/tos-alisg-i-aphluv4xwc-sg/fb96a11227f042edac2b8b9350dbfc05~tplv-aphluv4xwc-crop-webp:1336:1336.webp?dr=15592&t=555f072d&ps=933b5bde&shp=8dbd94bf&shcp=d741f1be&idc=my&from=2378011839",
    "source": "WIRETAP"
  },
  {
    "product_id": "1734429237864138433",
    "title": "Combo mix kopi so full  30 sachet mix so-tox senna 30 biji by ain hadi Candy",
    "sale_price_rm": "74.64",
    "original_price_rm": "92",
    "discount_percentage": "19%",
    "savings_amount": "Saving RM17.36",
    "units_sold": 10976,
    "rating_score": 4.9,
    "review_count": 2269,
    "shop_name": "Ainhadi Beauty",
    "shop_id": "7494537272820140737",
    "free_shipping": false,
    "product_url": "https://shop.tiktok.com/my/pdp/combo-mix-kopi-7-hari-by-ain-hadi-beauty-sedap-sachet-mix-so-tox/1734429237864138433",
    "image_url": "https://p16-oec-sg.ibyteimg.com/tos-alisg-i-aphluv4xwc-sg/cae437e7db9a43309e1a48b0ca461462~tplv-aphluv4xwc-crop-webp:764:764.webp?dr=15592&t=555f072d&ps=933b5bde&shp=8dbd94bf&shcp=d741f1be&idc=my&from=2378011839",
    "source": "WIRETAP"
  },
  {
    "product_id": "1734074269567190649",
    "title": "Blue wide-leg jeans New high-quality women's washed straight leg pants High-waisted casual wide-leg pants Seluar jeans kasual",
    "sale_price_rm": "25.9",
    "original_price_rm": "51.8",
    "discount_percentage": "50%",
    "savings_amount": "Saving RM25.90",
    "units_sold": 2881,
    "rating_score": 4.8,
    "review_count": 399,
    "shop_name": "UU fashion store",
    "shop_id": "7496084243715885689",
    "free_shipping": false,
    "product_url": "https://shop.tiktok.com/my/pdp/1734074269567190649",
    "image_url": "https://p16-oec-sg.ibyteimg.com/tos-alisg-i-aphluv4xwc-sg/d101ddec8bd343b6906c795b5aa3cb79~tplv-aphluv4xwc-crop-webp:800:800.webp?dr=15592&t=555f072d&ps=933b5bde&shp=8dbd94bf&shcp=d741f1be&idc=my&from=2378011839",
    "source": "WIRETAP"
  },
  {
    "product_id": "1733452236039750668",
    "title": "8 Warna, Velvet Matte Liquid Lipstick Lip Gloss Long,Pengilat Bibir Kalis Air Pusam, DUNUF,Gaya Selebriti  Tahan Lama, lipgloss lipmatte",
    "sale_price_rm": "4.98",
    "original_price_rm": "18.5",
    "discount_percentage": "73%",
    "savings_amount": "Saving RM13.52",
    "units_sold": 11879,
    "rating_score": 4.6,
    "review_count": 1707,
    "shop_name": "AINIPINK-",
    "shop_id": "8655862168951489548",
    "free_shipping": false,
    "product_url": "https://shop.tiktok.com/my/pdp/dunuf-lipstik-cair-matta-8-warna-tahan-lama-waterproof/1733452236039750668",
    "image_url": "https://p16-oec-sg.ibyteimg.com/tos-alisg-i-aphluv4xwc-sg/47eaf674fcfd4befb7b13c49d63aa534~tplv-aphluv4xwc-crop-webp:942:941.webp?dr=15592&t=555f072d&ps=933b5bde&shp=8dbd94bf&shcp=d741f1be&idc=my&from=2378011839",
    "source": "WIRETAP"
  },
  {
    "product_id": "1732002466877703370",
    "title": "BRAKE HOSE RS8 LCV8 Y15ZR Y16ZR LC135 RSX150 RS150 SYM VF3 R15 MT15 NVX NMAX REAR BRAKE HOSE RS8 90CM 60CM DEPAN BELAKANG",
    "sale_price_rm": "1.88",
    "original_price_rm": "5",
    "discount_percentage": "62%",
    "savings_amount": "Saving RM3.12",
    "units_sold": 11529,
    "rating_score": 4.9,
    "review_count": 3272,
    "shop_name": "SIM MOTOR POWER",
    "shop_id": "7494583747236169930",
    "free_shipping": false,
    "product_url": "https://shop.tiktok.com/my/pdp/hos-brek-rs8-90cm-60cm-depan-belakang-lcv8-y15zr-y16zr-rsx150-nvx-nmax/1732002466877703370",
    "image_url": "https://p16-oec-sg.ibyteimg.com/tos-alisg-i-aphluv4xwc-sg/eeb7aa6cfb7d45e4916830ed1542ef72~tplv-aphluv4xwc-crop-webp:1254:1254.webp?dr=15592&t=555f072d&ps=933b5bde&shp=8dbd94bf&shcp=d741f1be&idc=my&from=2378011839",
    "source": "WIRETAP"
  },
  {
    "product_id": "1729698751591777553",
    "title": "MOTION MOTORCYLE OIL FILTER Penapis Minyak Yamaha LC135 V1-V8 FZ150 Y15ZR FZ150I Lagenda 115 SRL115 FI Xmax250 R15 MT15",
    "sale_price_rm": "4.5",
    "original_price_rm": "9",
    "discount_percentage": "50%",
    "savings_amount": "Saving RM4.50",
    "units_sold": 13791,
    "rating_score": 4.9,
    "review_count": 3297,
    "shop_name": "Motion Malaysia",
    "shop_id": "7495033603890972945",
    "free_shipping": false,
    "product_url": "https://shop.tiktok.com/my/pdp/penapis-minyak-motion-yamaha-lc135-fz150-y15zr-formulasi-100-virgin-sijil-insurans-lonpac/1729698751591777553",
    "image_url": "https://p16-oec-sg.ibyteimg.com/tos-alisg-i-aphluv4xwc-sg/2ad42cde5f2643ea8610668138e1a313~tplv-aphluv4xwc-crop-webp:1024:1024.webp?dr=15592&t=555f072d&ps=933b5bde&shp=8dbd94bf&shcp=d741f1be&idc=my&from=2378011839",
    "source": "WIRETAP"
  },
  {
    "product_id": "1729651311619639144",
    "title": "Wireless Bras Women Cotton Bra Full Coverage 34-42 Cup B Design Floral Flower Baju Dalam Wanita Tanpa Dawai",
    "sale_price_rm": "6.89",
    "original_price_rm": "19.9",
    "discount_percentage": "65%",
    "savings_amount": "Saving RM13.01",
    "units_sold": 32331,
    "rating_score": 4.8,
    "review_count": 6715,
    "shop_name": "FirstLady",
    "shop_id": "7494704267430759272",
    "free_shipping": false,
    "product_url": "https://shop.tiktok.com/my/pdp/bra-kapas-tanpa-wayar-wanita-reka-bentuk-bunga-selesa-bergaya/1729651311619639144",
    "image_url": "https://p16-oec-sg.ibyteimg.com/tos-alisg-i-aphluv4xwc-sg/a8abde3cd5c04ed4b69020b532bba6fd~tplv-aphluv4xwc-crop-webp:723:723.webp?dr=15592&t=555f072d&ps=933b5bde&shp=8dbd94bf&shcp=d741f1be&idc=my&from=2378011839",
    "source": "WIRETAP"
  },
  {
    "product_id": "1730886578023335516",
    "title": "Purfresh 2026 Baharu Car Air Freshener 185g  Minyak Pewangi Kereta Penyegar Udara Kereta Tahan Lama,Car perfume,Ekstrak Tumbuhan Automotive Interior",
    "sale_price_rm": "9.9",
    "original_price_rm": "19.9",
    "discount_percentage": "50%",
    "savings_amount": "Saving RM10.00",
    "units_sold": 293144,
    "rating_score": 4.7,
    "review_count": 55428,
    "shop_name": "ClarkkaraMY",
    "shop_id": "7496013334290270812",
    "free_shipping": false,
    "product_url": "https://shop.tiktok.com/my/pdp/aroma-mobil-purfresh-2025-lembut-segar-berpanjangan/1730886578023335516",
    "image_url": "https://p16-oec-sg.ibyteimg.com/tos-alisg-i-aphluv4xwc-sg/802298e2f9f343cc811c0a530d0c33f1~tplv-aphluv4xwc-crop-webp:1600:1600.webp?dr=15592&t=555f072d&ps=933b5bde&shp=8dbd94bf&shcp=d741f1be&idc=my&from=2378011839",
    "source": "WIRETAP"
  },
  {
    "product_id": "1729482997062404051",
    "title": "[WOMANHUB]Lip Butter Berwarna Semula Jadi Organik dengan Vitamin E + Lip Scrub Percuma untuk Bibir Kering, Sensitif,Merekah",
    "sale_price_rm": "3.99",
    "original_price_rm": "25.9",
    "discount_percentage": "85%",
    "savings_amount": "Saving RM21.91",
    "units_sold": 248522,
    "rating_score": 4.8,
    "review_count": 59298,
    "shop_name": "WOMANHUB BEAUTY",
    "shop_id": "7495279591439174611",
    "free_shipping": false,
    "product_url": "https://shop.tiktok.com/my/pdp/natural-tinted-lip-butter-dari-womanhub-pelembap-bibir-tanpa-paraben-sesuai-untuk-ekzema/1729482997062404051",
    "image_url": "https://p16-oec-sg.ibyteimg.com/tos-alisg-i-aphluv4xwc-sg/46e94c0adc46482c869cbab8bb924a00~tplv-aphluv4xwc-crop-webp:1280:1280.webp?dr=15592&t=555f072d&ps=933b5bde&shp=8dbd94bf&shcp=d741f1be&idc=my&from=2378011839",
    "source": "WIRETAP"
  },
  {
    "product_id": "1730759929484575932",
    "title": "Unisex Plain Baseball Cap Ready Stock Adjustable / Topi Baseball",
    "sale_price_rm": "2.5",
    "original_price_rm": "0.00",
    "discount_percentage": "",
    "savings_amount": "",
    "units_sold": 11556,
    "rating_score": 4.8,
    "review_count": 289,
    "shop_name": "ZK Homeware",
    "shop_id": "7496036601660016828",
    "free_shipping": false,
    "product_url": "https://shop.tiktok.com/my/pdp/topi-baseball-uniseks-kanvas-boleh-laras-pelbagai-warna/1730759929484575932",
    "image_url": "https://p16-oec-sg.ibyteimg.com/tos-alisg-i-aphluv4xwc-sg/027e8f9b3d2b4c6a8506ae579d32c20f~tplv-aphluv4xwc-crop-webp:748:748.webp?dr=15592&t=555f072d&ps=933b5bde&shp=8dbd94bf&shcp=d741f1be&idc=my&from=2378011839",
    "source": "WIRETAP"
  },
  {
    "product_id": "1736239274318399448",
    "title": "Cermin lembut akrilik pelekat dinding dengan daya melekat sendiri untuk bilik mandi/bateri rumah; sesuai untuk pemasangan berkeping dan cermin solekan; model tular; cermin akrilik lembut pelekat dinding dengan daya melekat sendiri untuk bilik mandi/bateri",
    "sale_price_rm": "14",
    "original_price_rm": "28",
    "discount_percentage": "50%",
    "savings_amount": "Saving RM14.00",
    "units_sold": 1609,
    "rating_score": 3.9,
    "review_count": 99,
    "shop_name": "fish843",
    "shop_id": "8674527192096540632",
    "free_shipping": false,
    "product_url": "https://shop.tiktok.com/my/pdp/1736239274318399448",
    "image_url": "https://p16-oec-sg.ibyteimg.com/tos-alisg-i-aphluv4xwc-sg/0c229cb3f937498cbcffff2b725bcf72~tplv-aphluv4xwc-crop-webp:2048:2048.webp?dr=15592&t=555f072d&ps=933b5bde&shp=8dbd94bf&shcp=d741f1be&idc=my&from=2378011839",
    "source": "WIRETAP"
  },
  {
    "product_id": "1733934537224324755",
    "title": "Cadar Tilam Aloe Cotton 800tc 2IN1 Single Queen King 4IN1 Fitted Bedsheet Set Dengan Bolster Case Kualiti Lembut Dan Selesa",
    "sale_price_rm": "10.09",
    "original_price_rm": "13.39",
    "discount_percentage": "25%",
    "savings_amount": "Saving RM3.30",
    "units_sold": 14323,
    "rating_score": 4.8,
    "review_count": 2587,
    "shop_name": "Easyonline",
    "shop_id": "7494558885998201491",
    "free_shipping": false,
    "product_url": "https://shop.tiktok.com/my/pdp/1733934537224324755",
    "image_url": "https://p16-oec-sg.ibyteimg.com/tos-alisg-i-aphluv4xwc-sg/aebfd1d00ee84df6bec44a781abe41aa~tplv-aphluv4xwc-crop-webp:1280:1280.webp?dr=15592&t=555f072d&ps=933b5bde&shp=8dbd94bf&shcp=d741f1be&idc=my&from=2378011839",
    "source": "WIRETAP"
  },
  {
    "product_id": "1736055127522903825",
    "title": "Blue Edp 35ml Perfume For Man",
    "sale_price_rm": "3.9",
    "original_price_rm": "12",
    "discount_percentage": "68%",
    "savings_amount": "Saving RM8.10",
    "units_sold": 1184,
    "rating_score": 4.6,
    "review_count": 212,
    "shop_name": "The Essence Shop",
    "shop_id": "7494255060775634705",
    "free_shipping": false,
    "product_url": "https://shop.tiktok.com/my/pdp/1736055127522903825",
    "image_url": "https://p16-oec-sg.ibyteimg.com/tos-alisg-i-aphluv4xwc-sg/45f333a44df741da81d182406a027209~tplv-aphluv4xwc-crop-webp:1086:1448.webp?dr=15592&t=555f072d&ps=933b5bde&shp=8dbd94bf&shcp=d741f1be&idc=my&from=2378011839",
    "source": "WIRETAP"
  },
  {
    "product_id": "1729930021950751808",
    "title": "Botol Bayi, Anti-kembung, Botol berongga lebar, Reka Bentuk Mencegah Kembung, Kalis Kejutan dan Kalis Tercekik, Bebas BPA Babies Bottles Feeding Nursing Blue",
    "sale_price_rm": "2.99",
    "original_price_rm": "5.98",
    "discount_percentage": "50%",
    "savings_amount": "Saving RM2.99",
    "units_sold": 82052,
    "rating_score": 4.8,
    "review_count": 12720,
    "shop_name": "Cuddliverse-mkd",
    "shop_id": "7494741722184321088",
    "free_shipping": false,
    "product_url": "https://shop.tiktok.com/my/pdp/botol-bayi-anti-kembung-berongga-lebar-kalis-kejutan-bpa/1729930021950751808",
    "image_url": "https://p16-oec-sg.ibyteimg.com/tos-alisg-i-aphluv4xwc-sg/fa95e80b683b45a1905187223696409b~tplv-aphluv4xwc-crop-webp:2000:2000.webp?dr=15592&t=555f072d&ps=933b5bde&shp=8dbd94bf&shcp=d741f1be&idc=my&from=2378011839",
    "source": "WIRETAP"
  },
  {
    "product_id": "1729583355106199497",
    "title": "H9 pro MAX,Skrin Sentuh HD 2.01 dengan Permainan, Bluetooth, Muzik, Terima / Panggilan Dail, Padat dan Mudah Alih, dengan Pemantau Tekanan, Peranti Jam randik, Boleh Dipakai,smart watch ultra smartwatch tan handphone h3 ultra smart watch kids boy women",
    "sale_price_rm": "19.6",
    "original_price_rm": "189",
    "discount_percentage": "90%",
    "savings_amount": "Saving RM169.40",
    "units_sold": 228928,
    "rating_score": 4.7,
    "review_count": 36431,
    "shop_name": "Sole EC MY",
    "shop_id": "7495651614924508105",
    "free_shipping": false,
    "product_url": "https://shop.tiktok.com/my/pdp/jam-tangan-pintar-ultra-smart-watch-tanpa-telefon-anak-laki-laki-wanita-skrin-sentuh-hd-2-01-inci-bl/1729583355106199497",
    "image_url": "https://p19-oec-sg.ibyteimg.com/tos-alisg-i-aphluv4xwc-sg/8dee5edf85414710a2e02567e6060a43~tplv-aphluv4xwc-crop-webp:1000:1000.webp?dr=15592&t=555f072d&ps=933b5bde&shp=8dbd94bf&shcp=d741f1be&idc=my&from=2378011839",
    "source": "WIRETAP"
  },
  {
    "product_id": "1735808631624336556",
    "title": "mystery dumpling Kreatif Warna Pelangi Mainan Squishy Bentuk Dumpling Naik Perlahan Pemulihan Perlahan Ladu Lembut Cubit Comel dan Lembut Bola Fidget Sensori Keresahan ADHD",
    "sale_price_rm": "6.39",
    "original_price_rm": "13.6",
    "discount_percentage": "53%",
    "savings_amount": "Saving RM7.21",
    "units_sold": 736,
    "rating_score": 4.7,
    "review_count": 105,
    "shop_name": "Lizziw",
    "shop_id": "8670351268209657004",
    "free_shipping": false,
    "product_url": "https://shop.tiktok.com/my/pdp/1735808631624336556",
    "image_url": "https://p16-oec-sg.ibyteimg.com/tos-alisg-i-aphluv4xwc-sg/0e74ccc39a1e4801817c47a0d448546e~tplv-aphluv4xwc-crop-webp:1000:1000.webp?dr=15592&t=555f072d&ps=933b5bde&shp=8dbd94bf&shcp=d741f1be&idc=my&from=2378011839",
    "source": "WIRETAP"
  },
  {
    "product_id": "1733042793377662863",
    "title": "11000-MYYQA-after-Commodity accessory and screwsspecifically usedforin-store after-sales serviceHardware,official authentic Kitchen Spice Rack Kitchen Rak Dapur Rak  After Sale Service Special for repair and reissue of goods",
    "sale_price_rm": "99",
    "original_price_rm": "0.00",
    "discount_percentage": "",
    "savings_amount": "",
    "units_sold": 2893,
    "rating_score": 5.0,
    "review_count": 1,
    "shop_name": "Drew.H",
    "shop_id": "7495141360066399119",
    "free_shipping": false,
    "product_url": "https://shop.tiktok.com/my/pdp/aksesori-sekrup-pasca-jualan-rasmi-autentik-hardware/1733042793377662863",
    "image_url": "https://p16-oec-sg.ibyteimg.com/tos-alisg-i-aphluv4xwc-sg/40afbb6f672e41b4b2afa8c0acc87c67~tplv-aphluv4xwc-crop-webp:750:760.webp?dr=15592&t=555f072d&ps=933b5bde&shp=8dbd94bf&shcp=d741f1be&idc=my&from=2378011839",
    "source": "WIRETAP"
  },
  {
    "product_id": "1731640192535725111",
    "title": "【 FREE SHIPPING 】Cooling Plate Design | Rechargeable 100–199 Speed Adjustable | Strong Wind Digital Display | Portable Home Office Fan | Kipas Mini Boleh Cas",
    "sale_price_rm": "16.99",
    "original_price_rm": "75",
    "discount_percentage": "77%",
    "savings_amount": "Saving RM58.01",
    "units_sold": 99589,
    "rating_score": 4.7,
    "review_count": 22188,
    "shop_name": "AllGoodthings",
    "shop_id": "7494710558367320119",
    "free_shipping": false,
    "product_url": "https://shop.tiktok.com/my/pdp/kipas-mini-turbo-6000mah-100-199-kelajuan-mudah-alih/1731640192535725111",
    "image_url": "https://p16-oec-sg.ibyteimg.com/tos-alisg-i-aphluv4xwc-sg/8251cb76160943cf82f160cbeb7da23c~tplv-aphluv4xwc-crop-webp:1254:1254.webp?dr=15592&t=555f072d&ps=933b5bde&shp=8dbd94bf&shcp=d741f1be&idc=my&from=2378011839",
    "source": "WIRETAP"
  },
  {
    "product_id": "1735223253843478215",
    "title": "Touch N’ Go NFC Card - Kad TN’G Classic Edition (Fast Shipping) (Original )",
    "sale_price_rm": "11.2",
    "original_price_rm": "0.00",
    "discount_percentage": "",
    "savings_amount": "",
    "units_sold": 2552,
    "rating_score": 4.9,
    "review_count": 446,
    "shop_name": "Nicole88",
    "shop_id": "7494551442542855879",
    "free_shipping": false,
    "product_url": "https://shop.tiktok.com/my/pdp/1735223253843478215",
    "image_url": "https://p16-oec-sg.ibyteimg.com/tos-alisg-i-aphluv4xwc-sg/d2edf6c01b2b4f0a9ccbdc2a62ba57b0~tplv-aphluv4xwc-crop-webp:790:790.webp?dr=15592&t=555f072d&ps=933b5bde&shp=8dbd94bf&shcp=d741f1be&idc=my&from=2378011839",
    "source": "WIRETAP"
  },
  {
    "product_id": "1730707696650651408",
    "title": "Berbaloii Home Cadar Kartun Single 2in1 Cadar Budak Bedsheet Queen Cartoon 4in1 Kids Bedsheet Soft",
    "sale_price_rm": "7.98",
    "original_price_rm": "0.00",
    "discount_percentage": "",
    "savings_amount": "",
    "units_sold": 18465,
    "rating_score": 4.8,
    "review_count": 2741,
    "shop_name": "berbaloiihome",
    "shop_id": "7496032757949500176",
    "free_shipping": false,
    "product_url": "https://shop.tiktok.com/my/pdp/cadar-kartun-2in1-berbaloii-aloe-cotton-fitted-warna-menarik/1730707696650651408",
    "image_url": "https://p16-oec-sg.ibyteimg.com/tos-alisg-i-aphluv4xwc-sg/6474a09513284270bd69fe5c2adf78a9~tplv-aphluv4xwc-crop-webp:1200:1200.webp?dr=15592&t=555f072d&ps=933b5bde&shp=8dbd94bf&shcp=d741f1be&idc=my&from=2378011839",
    "source": "WIRETAP"
  },
  {
    "product_id": "1735065734604620878",
    "title": "RYTON TIMES Pakaian Pembentuk Badan | Tali pembentuk pinggang uniseks dengan kompresi boleh laras dan pengencangan pinggang elastik, diperbuat daripada kain selesa sesuai untuk sukan, kecergasan dan pemakaian harian",
    "sale_price_rm": "20.7",
    "original_price_rm": "83",
    "discount_percentage": "75%",
    "savings_amount": "Saving RM62.30",
    "units_sold": 18950,
    "rating_score": 4.9,
    "review_count": 2915,
    "shop_name": "RYTON TIMES SPORT",
    "shop_id": "7494537146722911310",
    "free_shipping": false,
    "product_url": "https://shop.tiktok.com/my/pdp/1735065734604620878",
    "image_url": "https://p16-oec-sg.ibyteimg.com/tos-alisg-i-aphluv4xwc-sg/af14725294ad4289b78de287f137c9b0~tplv-aphluv4xwc-crop-webp:1254:1254.webp?dr=15592&t=555f072d&ps=933b5bde&shp=8dbd94bf&shcp=d741f1be&idc=my&from=2378011839",
    "source": "WIRETAP"
  },
  {
    "product_id": "1733244995739027031",
    "title": "Laser Pemutih Serum 20ML FREE Cream Pemutih",
    "sale_price_rm": "25.8",
    "original_price_rm": "26.9",
    "discount_percentage": "4%",
    "savings_amount": "Saving RM1.10",
    "units_sold": 10205,
    "rating_score": 4.8,
    "review_count": 1212,
    "shop_name": "Mumya Beaute",
    "shop_id": "7494680028844886615",
    "free_shipping": false,
    "product_url": "https://shop.tiktok.com/my/pdp/1733244995739027031",
    "image_url": "https://p16-oec-sg.ibyteimg.com/tos-alisg-i-aphluv4xwc-sg/5f664aa0628d4bf080da2c59e16ab092~tplv-aphluv4xwc-crop-webp:800:800.webp?dr=15592&t=555f072d&ps=933b5bde&shp=8dbd94bf&shcp=d741f1be&idc=my&from=2378011839",
    "source": "WIRETAP"
  },
  {
    "product_id": "1736091106946025338",
    "title": "Tong beras rumah tahan serangga dan lembap, kedap, gred makanan, untuk tepung dan beras, kapasiti besar, kotak simpanan/penyimpanan Supplies Jewellery Box pakaian almari pakaian kotak & tong penyimpanan",
    "sale_price_rm": "24.15",
    "original_price_rm": "78.9",
    "discount_percentage": "69%",
    "savings_amount": "Saving RM54.75",
    "units_sold": 148,
    "rating_score": 4.9,
    "review_count": 20,
    "shop_name": "EasyLife HomeStore",
    "shop_id": "7494696176187443066",
    "free_shipping": false,
    "product_url": "https://shop.tiktok.com/my/pdp/1736091106946025338",
    "image_url": "https://p16-oec-sg.ibyteimg.com/tos-alisg-i-aphluv4xwc-sg/f0806228f5d24cc0baac6c8d5ea5a5c8~tplv-aphluv4xwc-crop-webp:1500:1500.webp?dr=15592&t=555f072d&ps=933b5bde&shp=8dbd94bf&shcp=d741f1be&idc=my&from=2378011839",
    "source": "WIRETAP"
  },
  {
    "product_id": "1733137839598437682",
    "title": "【Ramai Beli】GMEELAN Glabridin Long-Lasting Foundation Stick Foundation Stick 2-in-1 Flash Makeup 12 Hour Long Lasting Oil control & Nourishment",
    "sale_price_rm": "27",
    "original_price_rm": "55.1",
    "discount_percentage": "51%",
    "savings_amount": "Saving RM28.10",
    "units_sold": 61818,
    "rating_score": 4.8,
    "review_count": 13271,
    "shop_name": "GMEELAN.Malaysia",
    "shop_id": "7494703696583887154",
    "free_shipping": false,
    "product_url": "https://shop.tiktok.com/my/pdp/gmeelan-black-truffle-zinc-pca-long-lasting-foundation-stick/1733137839598437682",
    "image_url": "https://p16-oec-sg.ibyteimg.com/tos-alisg-i-aphluv4xwc-sg/f61cb0378eef44f499ab8939088ca9c5~tplv-aphluv4xwc-crop-webp:1200:1200.webp?dr=15592&t=555f072d&ps=933b5bde&shp=8dbd94bf&shcp=d741f1be&idc=my&from=2378011839",
    "source": "WIRETAP"
  },
  {
    "product_id": "1733206391919051779",
    "title": "ELGINI E16392 Jaket Hujan Bertopi Bergaya S-XXL | Stylish Hooded Rain Jacket",
    "sale_price_rm": "20.99",
    "original_price_rm": "50.9",
    "discount_percentage": "59%",
    "savings_amount": "Saving RM29.91",
    "units_sold": 42741,
    "rating_score": 4.9,
    "review_count": 10020,
    "shop_name": "ELGINI MALAYSIA",
    "shop_id": "7494587065580685315",
    "free_shipping": false,
    "product_url": "https://shop.tiktok.com/my/pdp/jaket-hujan-bertopi-elgini-e16392-kalis-air-ringan-bernafas/1733206391919051779",
    "image_url": "https://p16-oec-va.ibyteimg.com/tos-maliva-i-o3syd03w52-us/e2be5585c620491dba5bffd0eba5a2a2~tplv-o3syd03w52-crop-webp:3000:3000.webp?dr=15592&t=555f072d&ps=933b5bde&shp=8dbd94bf&shcp=d741f1be&idc=my&from=2378011839",
    "source": "WIRETAP"
  },
  {
    "product_id": "1729517992028440302",
    "title": "THE HIJAB CO NEA FULL COVER TIE BACK VISCOSE COTTON INNER NECK",
    "sale_price_rm": "22.9",
    "original_price_rm": "38",
    "discount_percentage": "40%",
    "savings_amount": "Saving RM15.10",
    "units_sold": 30866,
    "rating_score": 4.9,
    "review_count": 6292,
    "shop_name": "THE HIJAB CO",
    "shop_id": "7494662814471588590",
    "free_shipping": false,
    "product_url": "https://shop.tiktok.com/my/pdp/hijab-nea-full-cover-tie-back-anti-gelincir-ringan-selesa/1729517992028440302",
    "image_url": "https://p16-oec-sg.ibyteimg.com/tos-alisg-i-aphluv4xwc-sg/fbbe0f246de746bab0600dd6923b0154~tplv-aphluv4xwc-crop-webp:1280:1280.webp?dr=15592&t=555f072d&ps=933b5bde&shp=8dbd94bf&shcp=d741f1be&idc=my&from=2378011839",
    "source": "WIRETAP"
  },
  {
    "product_id": "1729615118689601564",
    "title": "Novencci Women's Outdoor Sport Shoes Sneakers (Ready Stock)",
    "sale_price_rm": "9.89",
    "original_price_rm": "25",
    "discount_percentage": "60%",
    "savings_amount": "Saving RM15.11",
    "units_sold": 88973,
    "rating_score": 4.7,
    "review_count": 13328,
    "shop_name": "NOVENCCI",
    "shop_id": "7494988793567479836",
    "free_shipping": false,
    "product_url": "https://shop.tiktok.com/my/pdp/kasut-sukan-wanita-novencci-stok-bila-bila-saiz-selesa/1729615118689601564",
    "image_url": "https://p16-oec-sg.ibyteimg.com/tos-alisg-i-aphluv4xwc-sg/0c2f7fa3609544ad8a17667e906da354~tplv-aphluv4xwc-crop-webp:1563:1563.webp?dr=15592&t=555f072d&ps=933b5bde&shp=8dbd94bf&shcp=d741f1be&idc=my&from=2378011839",
    "source": "WIRETAP"
  },
  {
    "product_id": "1729594153053030561",
    "title": "Tuam Herba Baby Set Pemanas Tuam babies Tuam bayi",
    "sale_price_rm": "5.5",
    "original_price_rm": "0.00",
    "discount_percentage": "",
    "savings_amount": "",
    "units_sold": 47633,
    "rating_score": 4.9,
    "review_count": 10408,
    "shop_name": "AFIYA BABY AND MOM",
    "shop_id": "7494815853673416865",
    "free_shipping": false,
    "product_url": "https://shop.tiktok.com/my/pdp/set-pemanas-tuam-bayi-herba-terbaik-dan-freegift-menarik/1729594153053030561",
    "image_url": "https://p16-oec-sg.ibyteimg.com/tos-alisg-i-aphluv4xwc-sg/01302ec5ed65484982f7e949235e9239~tplv-aphluv4xwc-crop-webp:1000:1000.webp?dr=15592&t=555f072d&ps=933b5bde&shp=8dbd94bf&shcp=d741f1be&idc=my&from=2378011839",
    "source": "WIRETAP"
  },
  {
    "product_id": "1734521878908339349",
    "title": "Rak Penapis Air 2 Tingkat Hitam dan Putih untuk kegunaan rumah",
    "sale_price_rm": "27.9",
    "original_price_rm": "39.9",
    "discount_percentage": "30%",
    "savings_amount": "Saving RM12.00",
    "units_sold": 17617,
    "rating_score": 4.7,
    "review_count": 3397,
    "shop_name": "Eaglerack",
    "shop_id": "7494739334421317781",
    "free_shipping": false,
    "product_url": "https://shop.tiktok.com/my/pdp/1734521878908339349",
    "image_url": "https://p16-oec-sg.ibyteimg.com/tos-alisg-i-aphluv4xwc-sg/725c864d840b43f79fbce5801c9c78ca~tplv-aphluv4xwc-crop-webp:1000:1000.webp?dr=15592&t=555f072d&ps=933b5bde&shp=8dbd94bf&shcp=d741f1be&idc=my&from=2378011839",
    "source": "WIRETAP"
  },
  {
    "product_id": "1729528034948121974",
    "title": "SIMPLE Kind to Skin Refreshing Facial Wash Gel 150ml",
    "sale_price_rm": "16.38",
    "original_price_rm": "27.3",
    "discount_percentage": "40%",
    "savings_amount": "Saving RM10.92",
    "units_sold": 5686,
    "rating_score": 4.9,
    "review_count": 903,
    "shop_name": "Watsons Malaysia",
    "shop_id": "7495042366241343862",
    "free_shipping": false,
    "product_url": "https://shop.tiktok.com/my/pdp/gel-cuci-wajah-menyegarkan-untuk-kulit-sensitif-150ml/1729528034948121974",
    "image_url": "https://p16-oec-va.ibyteimg.com/tos-maliva-i-o3syd03w52-us/e8dcca5a14fa47f18fdb389c164c1995~tplv-o3syd03w52-crop-webp:880:880.webp?dr=15592&t=555f072d&ps=933b5bde&shp=8dbd94bf&shcp=d741f1be&idc=my&from=2378011839",
    "source": "WIRETAP"
  },
  {
    "product_id": "1730639943092045612",
    "title": "K&K 35GRAMS TRIAL THERAPEUTIC KERALA BRIGHTENING HERBAL POWDER MANDIAN HERBA SAFFRON & ROSE 100% ORGANIC Whitening Body Care Glow Natural",
    "sale_price_rm": "6",
    "original_price_rm": "15",
    "discount_percentage": "60%",
    "savings_amount": "Saving RM9.00",
    "units_sold": 404302,
    "rating_score": 4.8,
    "review_count": 43495,
    "shop_name": "K&K SIGNATURE BEAUTY",
    "shop_id": "7494697014538636076",
    "free_shipping": false,
    "product_url": "https://shop.tiktok.com/my/pdp/serbuk-herbale-pencerah-kulit-organik-dengan-sereh-mawar/1730639943092045612",
    "image_url": "https://p16-oec-sg.ibyteimg.com/tos-alisg-i-aphluv4xwc-sg/80f10c36b5fa4dc5ac769598a3a0be37~tplv-aphluv4xwc-crop-webp:1215:1215.webp?dr=15592&t=555f072d&ps=933b5bde&shp=8dbd94bf&shcp=d741f1be&idc=my&from=2378011839",
    "source": "WIRETAP"
  },
  {
    "product_id": "1734307609771672822",
    "title": "T-shirt, fesyen Amerika, gaya baharu, gaya kampus, sesuai untuk lelaki dan wanita, serbaguna, tie-dye Solona, kapas tulen, leher bulat, lengan pendek, kasual, saiz M–3XL, tersedia dalam 6 warna",
    "sale_price_rm": "18.89",
    "original_price_rm": "36.77",
    "discount_percentage": "49%",
    "savings_amount": "Saving RM17.88",
    "units_sold": 2155,
    "rating_score": 4.7,
    "review_count": 316,
    "shop_name": "CHILLHOOD",
    "shop_id": "8660591513756009718",
    "free_shipping": false,
    "product_url": "https://shop.tiktok.com/my/pdp/t-shirt-fesyen-amerika-tie-dye-kapas-tulen-saiz-m-3xl/1734307609771672822",
    "image_url": "https://p16-oec-sg.ibyteimg.com/tos-alisg-i-aphluv4xwc-sg/119cb19229f844bd9cef40d3dc6fae02~tplv-aphluv4xwc-crop-webp:800:800.webp?dr=15592&t=555f072d&ps=933b5bde&shp=8dbd94bf&shcp=d741f1be&idc=my&from=2378011839",
    "source": "WIRETAP"
  },
  {
    "product_id": "1733881783565125563",
    "title": "NEW!! REENZA EzyTox Lemon Tea Drink 10g x 10 sachet per box Minuman",
    "sale_price_rm": "1.5",
    "original_price_rm": "0.00",
    "discount_percentage": "",
    "savings_amount": "",
    "units_sold": 218312,
    "rating_score": 4.8,
    "review_count": 41875,
    "shop_name": "Reenza MY",
    "shop_id": "7496281311527013307",
    "free_shipping": false,
    "product_url": "https://shop.tiktok.com/my/pdp/1733881783565125563",
    "image_url": "https://p16-oec-sg.ibyteimg.com/tos-alisg-i-aphluv4xwc-sg/d8e82895076f4f7383a0ce803decd81d~tplv-aphluv4xwc-crop-webp:731:731.webp?dr=15592&t=555f072d&ps=933b5bde&shp=8dbd94bf&shcp=d741f1be&idc=my&from=2378011839",
    "source": "WIRETAP"
  },
  {
    "product_id": "1733594296043930828",
    "title": "【Dari Johor】ProMan Seluar Kasual Lelaki Loose Pants Outdoor Hiking Mountain Climbing Casual Pants Celana Tentera Gaya",
    "sale_price_rm": "14.45",
    "original_price_rm": "35",
    "discount_percentage": "59%",
    "savings_amount": "Saving RM20.55",
    "units_sold": 17602,
    "rating_score": 4.7,
    "review_count": 2676,
    "shop_name": "ProManshop",
    "shop_id": "7495624411613006028",
    "free_shipping": false,
    "product_url": "https://shop.tiktok.com/my/pdp/proman-seluar-kasual-lelaki-gaya-tentera-loose-pants-outdoor-hiking/1733594296043930828",
    "image_url": "https://p16-oec-va.ibyteimg.com/tos-maliva-i-o3syd03w52-us/83611e270cb54cb8a3fab7e907b20bff~tplv-o3syd03w52-crop-webp:800:800.webp?dr=15592&t=555f072d&ps=933b5bde&shp=8dbd94bf&shcp=d741f1be&idc=my&from=2378011839",
    "source": "WIRETAP"
  },
  {
    "product_id": "1736358693339826137",
    "title": "pos laju dari malaysia Seluar Sweatpants Wide Leg, Gaya Vintage Santai, Longgar, Panjang Lantai Kasual, Seluar Sukan Serbaguna, Pakaian Wanita Kasual",
    "sale_price_rm": "16.06",
    "original_price_rm": "50",
    "discount_percentage": "68%",
    "savings_amount": "Saving RM33.94",
    "units_sold": 332,
    "rating_score": 4.8,
    "review_count": 13,
    "shop_name": "Huangmei County Shaima Trading Co Ltd b",
    "shop_id": "8676803996147746777",
    "free_shipping": false,
    "product_url": "https://shop.tiktok.com/my/pdp/1736358693339826137",
    "image_url": "https://p16-oec-sg.ibyteimg.com/tos-alisg-i-aphluv4xwc-sg/ec2c60e1764442d382a1155f0e9a2a71~tplv-aphluv4xwc-crop-webp:800:800.webp?dr=15592&t=555f072d&ps=933b5bde&shp=8dbd94bf&shcp=d741f1be&idc=my&from=2378011839",
    "source": "WIRETAP"
  },
  {
    "product_id": "1734362300698560271",
    "title": "Set rawatan jerawat sepanjang malam lengkap – pembersih jerawat, penghilang parut, dan pelembap untuk kulit yang mudah berjerawat; 4 langkah – Blanc Nature",
    "sale_price_rm": "960.24",
    "original_price_rm": "1173.65",
    "discount_percentage": "18%",
    "savings_amount": "Saving RM213.41",
    "units_sold": 1,
    "rating_score": 0.0,
    "review_count": 0,
    "shop_name": "Blanc Nature",
    "shop_id": "8656762593062127375",
    "free_shipping": false,
    "product_url": "https://shop.tiktok.com/my/pdp/1734362300698560271",
    "image_url": "https://p16-oec-sg.ibyteimg.com/tos-alisg-i-aphluv4xwc-sg/3e7630b8624046b4a80a2b610a32f4ea~tplv-aphluv4xwc-crop-webp:1200:1200.webp?dr=15592&t=555f072d&ps=933b5bde&shp=8dbd94bf&shcp=d741f1be&idc=my&from=2378011839",
    "source": "WIRETAP"
  },
  {
    "product_id": "1731579222455650228",
    "title": "American-style Waterproof Sports Assault Pants Lelaki Streetwear Trendy Brand Loose Pants Outdoor Hiking Mountain Climbing Casual Pants Celana Tentera Gaya seluar baggy sekolah",
    "sale_price_rm": "13.98",
    "original_price_rm": "32",
    "discount_percentage": "56%",
    "savings_amount": "Saving RM18.02",
    "units_sold": 66015,
    "rating_score": 4.8,
    "review_count": 10507,
    "shop_name": "Pavilion Fashion.my",
    "shop_id": "7495867386746211252",
    "free_shipping": false,
    "product_url": "https://shop.tiktok.com/my/pdp/celana-tentera-gaya-amerika-lelaki-sporty-santai/1731579222455650228",
    "image_url": "https://p16-oec-sg.ibyteimg.com/tos-alisg-i-aphluv4xwc-sg/fe0a80d15a4941e38726fc58bf7972ef~tplv-aphluv4xwc-crop-webp:800:800.webp?dr=15592&t=555f072d&ps=933b5bde&shp=8dbd94bf&shcp=d741f1be&idc=my&from=2378011839",
    "source": "WIRETAP"
  },
  {
    "product_id": "1736202500408968778",
    "title": "DUBAI CHEWY COOKIE BY PIYAH 50gram Kunafa Marshmallow",
    "sale_price_rm": "7.5",
    "original_price_rm": "8.99",
    "discount_percentage": "17%",
    "savings_amount": "Saving RM1.49",
    "units_sold": 4015,
    "rating_score": 4.8,
    "review_count": 384,
    "shop_name": "PIYAH PERFUME",
    "shop_id": "7496007354129156682",
    "free_shipping": false,
    "product_url": "https://shop.tiktok.com/my/pdp/1736202500408968778",
    "image_url": "https://p16-oec-sg.ibyteimg.com/tos-alisg-i-aphluv4xwc-sg/82d8e68ad9b14392b9731f4330000183~tplv-aphluv4xwc-crop-webp:1254:1254.webp?dr=15592&t=555f072d&ps=933b5bde&shp=8dbd94bf&shcp=d741f1be&idc=my&from=2378011839",
    "source": "WIRETAP"
  },
  {
    "product_id": "1733633939030574824",
    "title": "Seluar Peluh Kaki Lebar, Gaya Malas Vintaj, Longgar, Panjang Lantai Kasual, Seluar Panjang Sukan Serba guna, Pakaian Wan",
    "sale_price_rm": "22.94",
    "original_price_rm": "49",
    "discount_percentage": "53%",
    "savings_amount": "Saving RM26.06",
    "units_sold": 31931,
    "rating_score": 4.8,
    "review_count": 6429,
    "shop_name": "Geworth Space",
    "shop_id": "7495968052179602152",
    "free_shipping": false,
    "product_url": "https://shop.tiktok.com/my/pdp/seluar-peluh-kaki-lebar-gaya-malas-vintaj-longgar-panjang/1733633939030574824",
    "image_url": "https://p16-oec-sg.ibyteimg.com/tos-alisg-i-aphluv4xwc-sg/341bd82b9b2741aaad16575dc5ace034~tplv-aphluv4xwc-crop-webp:1024:1024.webp?dr=15592&t=555f072d&ps=933b5bde&shp=8dbd94bf&shcp=d741f1be&idc=my&from=2378011839",
    "source": "WIRETAP"
  },
  {
    "product_id": "1733644631192667880",
    "title": "GEWORTH Seluar Peluh Kaki Lebar, Summer Gaya Malas Vintaj, Longgar, Panjang Lantai Kasual, Seluar Panjang Sukan Serba guna",
    "sale_price_rm": "13",
    "original_price_rm": "25",
    "discount_percentage": "48%",
    "savings_amount": "Saving RM12.00",
    "units_sold": 20128,
    "rating_score": 4.8,
    "review_count": 3199,
    "shop_name": "Geworth Space",
    "shop_id": "7495968052179602152",
    "free_shipping": false,
    "product_url": "https://shop.tiktok.com/my/pdp/seluar-peluh-kaki-lebar-gaya-malas-vintaj-panjang-lantai/1733644631192667880",
    "image_url": "https://p16-oec-sg.ibyteimg.com/tos-alisg-i-aphluv4xwc-sg/8234d938bf0447fdbc6d5156223039fd~tplv-aphluv4xwc-crop-webp:1024:1024.webp?dr=15592&t=555f072d&ps=933b5bde&shp=8dbd94bf&shcp=d741f1be&idc=my&from=2378011839",
    "source": "WIRETAP"
  },
  {
    "product_id": "1732993447570146875",
    "title": "PANDAEYES SHANICE HOLIDAY MOOD PANTS (CLO-CNXC0919LP)",
    "sale_price_rm": "24.88",
    "original_price_rm": "79.9",
    "discount_percentage": "69%",
    "savings_amount": "Saving RM55.02",
    "units_sold": 70644,
    "rating_score": 4.9,
    "review_count": 12164,
    "shop_name": "Panda eyes",
    "shop_id": "7494690922822208059",
    "free_shipping": false,
    "product_url": "https://shop.tiktok.com/my/pdp/pandaeyes-shanice-holiday-mood-pants-selesa-sepanjang-hari-gaya-moden/1732993447570146875",
    "image_url": "https://p16-oec-sg.ibyteimg.com/tos-alisg-i-aphluv4xwc-sg/9d9f47e38d2a43dca77587df2a49cf53~tplv-aphluv4xwc-crop-webp:1200:1200.webp?dr=15592&t=555f072d&ps=933b5bde&shp=8dbd94bf&shcp=d741f1be&idc=my&from=2378011839",
    "source": "WIRETAP"
  },
  {
    "product_id": "1736451680963036675",
    "title": "COUDASH B37 Fon telinga Bluetooth sepenuhnya tanpa wayar, kualiti bunyi pada tahap Hi‑Fi, pengurangan hingar AI semasa panggilan tanpa gangguan, bahan mesra kulit, reka bentuk ergonomik, buka penutup dan sambungkan, memenuhi keperluan pelbagai situasi dal",
    "sale_price_rm": "19.9",
    "original_price_rm": "299.9",
    "discount_percentage": "93%",
    "savings_amount": "Saving RM280.00",
    "units_sold": 31,
    "rating_score": 0.0,
    "review_count": 0,
    "shop_name": "COUDASH",
    "shop_id": "8676549204426720771",
    "free_shipping": false,
    "product_url": "https://shop.tiktok.com/my/pdp/1736451680963036675",
    "image_url": "https://p16-oec-sg.ibyteimg.com/tos-alisg-i-aphluv4xwc-sg/0b724a7304444bdda8206ea6ab6084c3~tplv-aphluv4xwc-crop-webp:2000:2000.webp?dr=15592&t=555f072d&ps=933b5bde&shp=8dbd94bf&shcp=d741f1be&idc=my&from=2378011839",
    "source": "WIRETAP"
  },
  {
    "product_id": "1736008251160495204",
    "title": "Seluar jeans wanita retro kasual gaya Y2K, pinggang tinggi, kaki lebar lurus, trendi",
    "sale_price_rm": "20",
    "original_price_rm": "45",
    "discount_percentage": "56%",
    "savings_amount": "Saving RM25.00",
    "units_sold": 881,
    "rating_score": 4.8,
    "review_count": 50,
    "shop_name": "JeanDart",
    "shop_id": "8673308934618907748",
    "free_shipping": false,
    "product_url": "https://shop.tiktok.com/my/pdp/1736008251160495204",
    "image_url": "https://p16-oec-sg.ibyteimg.com/tos-alisg-i-aphluv4xwc-sg/c701eaa554b4422aa067d15ac9fd20c9~tplv-aphluv4xwc-crop-webp:800:800.webp?dr=15592&t=555f072d&ps=933b5bde&shp=8dbd94bf&shcp=d741f1be&idc=my&from=2378011839",
    "source": "WIRETAP"
  },
  {
    "product_id": "1729550982771738420",
    "title": "AbangS Anak tudung Sarung kapas sejuk pink belacan Hijab",
    "sale_price_rm": "1.75",
    "original_price_rm": "7",
    "discount_percentage": "75%",
    "savings_amount": "Saving RM5.25",
    "units_sold": 2573659,
    "rating_score": 4.8,
    "review_count": 323581,
    "shop_name": "Kedai Abang S",
    "shop_id": "7494895405678234420",
    "free_shipping": false,
    "product_url": "https://shop.tiktok.com/my/pdp/anak-tudung-sarung-dusty-pink-abangs-soft-cotton-sejuk-selesa/1729550982771738420",
    "image_url": "https://p16-oec-sg.ibyteimg.com/tos-alisg-i-aphluv4xwc-sg/a4677be6f15142488763c68b47a85cf3~tplv-aphluv4xwc-crop-webp:600:600.webp?dr=15592&t=555f072d&ps=933b5bde&shp=8dbd94bf&shcp=d741f1be&idc=my&from=2378011839",
    "source": "WIRETAP"
  },
  {
    "product_id": "1735807803994965269",
    "title": "2026 latest AI Bluetooth earbuds GT-70 equipped with a brand-new intelligent voice translation engine, break language barriers for smooth communication. They feature true wireless technology, powerful bass and intelligent noise reduction.",
    "sale_price_rm": "23.88",
    "original_price_rm": "88",
    "discount_percentage": "73%",
    "savings_amount": "Saving RM64.12",
    "units_sold": 1370,
    "rating_score": 4.5,
    "review_count": 117,
    "shop_name": "Bluetooth shop -05",
    "shop_id": "7494264697649333525",
    "free_shipping": false,
    "product_url": "https://shop.tiktok.com/my/pdp/1735807803994965269",
    "image_url": "https://p16-oec-sg.ibyteimg.com/tos-alisg-i-aphluv4xwc-sg/9bf34430ae1f4ccd84d6b295aa27711f~tplv-aphluv4xwc-crop-webp:2048:2048.webp?dr=15592&t=555f072d&ps=933b5bde&shp=8dbd94bf&shcp=d741f1be&idc=my&from=2378011839",
    "source": "WIRETAP"
  },
  {
    "product_id": "1732254358741092079",
    "title": "FACERINNA-SERUM SUNSCREEN NIACINAMIDE BRIGHTENING Daily UVA/UVB Defense Evens Skin Tone SPF50+ PA+++ UV Protection Penjagaan Kulit",
    "sale_price_rm": "15",
    "original_price_rm": "49",
    "discount_percentage": "69%",
    "savings_amount": "Saving RM34.00",
    "units_sold": 225232,
    "rating_score": 4.8,
    "review_count": 42316,
    "shop_name": "Facerinna my",
    "shop_id": "7496280865449085679",
    "free_shipping": false,
    "product_url": "https://shop.tiktok.com/my/pdp/serum-pelindung-matahari-niacinamide-pencerah-spf50-pa/1732254358741092079",
    "image_url": "https://p16-oec-sg.ibyteimg.com/tos-alisg-i-aphluv4xwc-sg/586307eef7b440f2af771f3e7fea63e3~tplv-aphluv4xwc-crop-webp:1200:1200.webp?dr=15592&t=555f072d&ps=933b5bde&shp=8dbd94bf&shcp=d741f1be&idc=my&from=2378011839",
    "source": "WIRETAP"
  },
  {
    "product_id": "1736340101505254461",
    "title": "Anting-anting Berlian Moissanite Warna D Asli untuk Wanita, Emas Mawar, Berlian Bulat, Anting-anting Emas Mawar, Hadiah Istimewa R01",
    "sale_price_rm": "14.9",
    "original_price_rm": "2000",
    "discount_percentage": "99%",
    "savings_amount": "Saving RM1,985.10",
    "units_sold": 16,
    "rating_score": 0.0,
    "review_count": 0,
    "shop_name": "C.FOURTEEN.MY",
    "shop_id": "7495284589721192509",
    "free_shipping": false,
    "product_url": "https://shop.tiktok.com/my/pdp/1736340101505254461",
    "image_url": "https://p16-oec-sg.ibyteimg.com/tos-alisg-i-aphluv4xwc-sg/c4228ed1cc644d2c8c0ec3e4db2800fd~tplv-aphluv4xwc-crop-webp:1000:1000.webp?dr=15592&t=555f072d&ps=933b5bde&shp=8dbd94bf&shcp=d741f1be&idc=my&from=2378011839",
    "source": "WIRETAP"
  },
  {
    "product_id": "1734233285485626532",
    "title": "Nestle Milo Active-Go 900g Original Exp:07/2027",
    "sale_price_rm": "22.89",
    "original_price_rm": "25.89",
    "discount_percentage": "12%",
    "savings_amount": "Saving RM3.00",
    "units_sold": 1008,
    "rating_score": 4.8,
    "review_count": 114,
    "shop_name": "SURO ZONE ENTERPRISE",
    "shop_id": "7495158409315256484",
    "free_shipping": false,
    "product_url": "https://shop.tiktok.com/my/pdp/nestle-milo-active-go-900g-original-exp-03-2027-produk-popular/1734233285485626532",
    "image_url": "https://p16-oec-sg.ibyteimg.com/tos-alisg-i-aphluv4xwc-sg/e08a4245a42e462485e7e29b95dbdfb2~tplv-aphluv4xwc-crop-webp:800:800.webp?dr=15592&t=555f072d&ps=933b5bde&shp=8dbd94bf&shcp=d741f1be&idc=my&from=2378011839",
    "source": "WIRETAP"
  },
  {
    "product_id": "1735441210970310358",
    "title": "[New Colour Arrivals ]Pagani Gear Jam Tangan Wanita Ladies Rubber Quartz Watch PG-G2018",
    "sale_price_rm": "1230",
    "original_price_rm": "1250",
    "discount_percentage": "2%",
    "savings_amount": "Saving RM20.00",
    "units_sold": 1086,
    "rating_score": 4.9,
    "review_count": 229,
    "shop_name": "Rhapsody Time",
    "shop_id": "7495603321426250454",
    "free_shipping": false,
    "product_url": "https://shop.tiktok.com/my/pdp/1735441210970310358",
    "image_url": "https://p16-oec-sg.ibyteimg.com/tos-alisg-i-aphluv4xwc-sg/70c3d312a92348f3a4bc95540027a786~tplv-aphluv4xwc-crop-webp:1000:1000.webp?dr=15592&t=555f072d&ps=933b5bde&shp=8dbd94bf&shcp=d741f1be&idc=my&from=2378011839",
    "source": "WIRETAP"
  },
  {
    "product_id": "1732819595548918926",
    "title": "Mini Sport Cotton Jasmine - SML Premium Cotton Instant",
    "sale_price_rm": "11.99",
    "original_price_rm": "25",
    "discount_percentage": "52%",
    "savings_amount": "Saving RM13.01",
    "units_sold": 57334,
    "rating_score": 4.8,
    "review_count": 8423,
    "shop_name": "Heejab Hub",
    "shop_id": "7494773730894710926",
    "free_shipping": false,
    "product_url": "https://shop.tiktok.com/my/pdp/mini-sport-cotton-jasmine-saiz-s-ml-nyaman-serap-peluh/1732819595548918926",
    "image_url": "https://p16-oec-sg.ibyteimg.com/tos-alisg-i-aphluv4xwc-sg/a9b212f6337c4c5380dcec2661a3bb6a~tplv-aphluv4xwc-crop-webp:1200:1200.webp?dr=15592&t=555f072d&ps=933b5bde&shp=8dbd94bf&shcp=d741f1be&idc=my&from=2378011839",
    "source": "WIRETAP"
  },
  {
    "product_id": "1734985802442245566",
    "title": "Kardigan rajutan kelabu untuk wanita, sesuai untuk musim bunga dan luruh, pelindung matahari, pakaian luar musim panas, gaun camisole, selendang, penutup bilik berhawa dingin yang bergaya (Model 10)",
    "sale_price_rm": "8.63",
    "original_price_rm": "14.88",
    "discount_percentage": "42%",
    "savings_amount": "Saving RM6.25",
    "units_sold": 369,
    "rating_score": 0.0,
    "review_count": 0,
    "shop_name": "Luminous Threads GR",
    "shop_id": "8664131431051462078",
    "free_shipping": false,
    "product_url": "https://shop.tiktok.com/my/pdp/1734985802442245566",
    "image_url": "https://p16-oec-va.ibyteimg.com/tos-maliva-i-o3syd03w52-us/ee29aa0a4006440e9b1ee1e14ee54d9a~tplv-o3syd03w52-crop-webp:600:600.webp?dr=15592&t=555f072d&ps=933b5bde&shp=8dbd94bf&shcp=d741f1be&idc=my&from=2378011839",
    "source": "WIRETAP"
  },
  {
    "product_id": "1736254388625245777",
    "title": "Ikat Kepala Anjal Corak Polka Dot untuk Wanita Ikat Rambut Sukan Jenis Turban Lembut dan Elastik Lilitan Rambut Lebar Anti Licin Headbands",
    "sale_price_rm": "1.57",
    "original_price_rm": "4",
    "discount_percentage": "61%",
    "savings_amount": "Saving RM2.43",
    "units_sold": 657,
    "rating_score": 4.7,
    "review_count": 15,
    "shop_name": "Cinta Trinket MY",
    "shop_id": "8675415756532123217",
    "free_shipping": false,
    "product_url": "https://shop.tiktok.com/my/pdp/1736254388625245777",
    "image_url": "https://p16-oec-sg.ibyteimg.com/tos-alisg-i-aphluv4xwc-sg/a7fdc97b815943529091648f2c318271~tplv-aphluv4xwc-crop-webp:1200:1200.webp?dr=15592&t=555f072d&ps=933b5bde&shp=8dbd94bf&shcp=d741f1be&idc=my&from=2378011839",
    "source": "WIRETAP"
  },
  {
    "product_id": "1736091590049301674",
    "title": "MLBB Black Myth Wukong fon telinga kepala Bluetooth wayarles DIY dengan Hi‑Fi, Fon kepala pembatalan hingar ENC, Fon Telinga Bluetooth Terjemahan AI 140+ Bahasa, Fon Telinga kalis air, sesuai untuk sukan, serasi dengan iPhone dan Android",
    "sale_price_rm": "11.99",
    "original_price_rm": "339.9",
    "discount_percentage": "96%",
    "savings_amount": "Saving RM327.91",
    "units_sold": 1421,
    "rating_score": 4.8,
    "review_count": 86,
    "shop_name": "ERAZER MLBB WUKONG MY Store",
    "shop_id": "8660134551015294122",
    "free_shipping": false,
    "product_url": "https://shop.tiktok.com/my/pdp/1736091590049301674",
    "image_url": "https://p16-oec-sg.ibyteimg.com/tos-alisg-i-aphluv4xwc-sg/2717e4a4fbd9466ca6c17b16134cd1f6~tplv-aphluv4xwc-crop-webp:1000:1000.webp?dr=15592&t=555f072d&ps=933b5bde&shp=8dbd94bf&shcp=d741f1be&idc=my&from=2378011839",
    "source": "WIRETAP"
  },
  {
    "product_id": "1733676130440939337",
    "title": "CHOMON @ Chocojar Monster Besar Gedabak 1200ml 440 gram Kokojar Balang Cereal Coklat Gelap Chocojar Premium Choco jar",
    "sale_price_rm": "16.99",
    "original_price_rm": "20",
    "discount_percentage": "15%",
    "savings_amount": "Saving RM3.01",
    "units_sold": 144078,
    "rating_score": 4.8,
    "review_count": 26305,
    "shop_name": "N.A Chocojar",
    "shop_id": "7494906776955358025",
    "free_shipping": false,
    "product_url": "https://shop.tiktok.com/my/pdp/1733676130440939337",
    "image_url": "https://p16-oec-sg.ibyteimg.com/tos-alisg-i-aphluv4xwc-sg/ebb21e31be4740bca66f7f9209e22a75~tplv-aphluv4xwc-crop-webp:1080:1080.webp?dr=15592&t=555f072d&ps=933b5bde&shp=8dbd94bf&shcp=d741f1be&idc=my&from=2378011839",
    "source": "WIRETAP"
  },
  {
    "product_id": "1731762852641474081",
    "title": "TATIZSKINCARE NEWW UPDATED PRICE",
    "sale_price_rm": "45.6",
    "original_price_rm": "0.00",
    "discount_percentage": "",
    "savings_amount": "",
    "units_sold": 13464,
    "rating_score": 4.9,
    "review_count": 1907,
    "shop_name": "GOZELLE BEAUTY",
    "shop_id": "7495887488839354913",
    "free_shipping": false,
    "product_url": "https://shop.tiktok.com/my/pdp/krim-penjagaan-kulit-skincare-harga-terkini-dapatkan-sekarang/1731762852641474081",
    "image_url": "https://p16-oec-sg.ibyteimg.com/tos-alisg-i-aphluv4xwc-sg/7f6efc51910448419f2c1e1e9f40d7b0~tplv-aphluv4xwc-crop-webp:1200:1200.webp?dr=15592&t=555f072d&ps=933b5bde&shp=8dbd94bf&shcp=d741f1be&idc=my&from=2378011839",
    "source": "WIRETAP"
  },
  {
    "product_id": "1736476033748206825",
    "title": "pos laju dari malaysia Seluar Sweatpants Wide Leg, Gaya Vintage Santai, Longgar, Panjang Lantai Kasual, Seluar Sukan Serbaguna, Pakaian Wanita Kasual",
    "sale_price_rm": "14.75",
    "original_price_rm": "33.89",
    "discount_percentage": "56%",
    "savings_amount": "Saving RM19.14",
    "units_sold": 47,
    "rating_score": 4.0,
    "review_count": 4,
    "shop_name": "ZenWearStudio",
    "shop_id": "8677035101505291497",
    "free_shipping": false,
    "product_url": "https://shop.tiktok.com/my/pdp/1736476033748206825",
    "image_url": "https://p16-oec-sg.ibyteimg.com/tos-alisg-i-aphluv4xwc-sg/ec2c60e1764442d382a1155f0e9a2a71~tplv-aphluv4xwc-crop-webp:800:800.webp?dr=15592&t=555f072d&ps=933b5bde&shp=8dbd94bf&shcp=d741f1be&idc=my&from=2378011839",
    "source": "WIRETAP"
  },
  {
    "product_id": "1729568172455855544",
    "title": "CUBRE MI BIG CAT EDITION 9IN1",
    "sale_price_rm": "16.99",
    "original_price_rm": "0.00",
    "discount_percentage": "",
    "savings_amount": "",
    "units_sold": 253495,
    "rating_score": 4.9,
    "review_count": 41201,
    "shop_name": "Cubremi",
    "shop_id": "7494693371473136056",
    "free_shipping": false,
    "product_url": "https://shop.tiktok.com/my/pdp/cubre-mi-eyeshadow-palette-8-dalam-1-pigmented-dan-berkilau-untuk-pelbagai-gaya/1729568172455855544",
    "image_url": "https://p16-oec-sg.ibyteimg.com/tos-alisg-i-aphluv4xwc-sg/def5479a69654bb5a3645643f0e2d548~tplv-aphluv4xwc-crop-webp:836:836.webp?dr=15592&t=555f072d&ps=933b5bde&shp=8dbd94bf&shcp=d741f1be&idc=my&from=2378011839",
    "source": "WIRETAP"
  },
  {
    "product_id": "1735448420477863108",
    "title": "Viral Comel Patung Anjing Miniatur Golden Retriever Labrador Realistik Hiasan Resin Taman Rumah Meja Pejabat Best Seller Ready Stock Malaysia",
    "sale_price_rm": "8.27",
    "original_price_rm": "15.31",
    "discount_percentage": "46%",
    "savings_amount": "Saving RM7.04",
    "units_sold": 0,
    "rating_score": 0.0,
    "review_count": 0,
    "shop_name": "Verva Home",
    "shop_id": "8667335441596384452",
    "free_shipping": false,
    "product_url": "https://shop.tiktok.com/my/pdp/patung-anjing-golden-retriever-miniatur-realistik-hiasan-rumah-taman/1735448420477863108",
    "image_url": "https://p16-oec-sg.ibyteimg.com/tos-alisg-i-aphluv4xwc-sg/cc37053b859b4b79bdc704919ed7a069~tplv-aphluv4xwc-crop-webp:800:800.webp?dr=15592&t=555f072d&ps=933b5bde&shp=8dbd94bf&shcp=d741f1be&idc=my&from=2378011839",
    "source": "WIRETAP"
  },
  {
    "product_id": "1734944123625244630",
    "title": "2000AMP Heavy Duty Jumper Cables 4M Emergency Car Battery Jump Starter Cables with Copper Clamps for Automotive Engine",
    "sale_price_rm": "20",
    "original_price_rm": "50",
    "discount_percentage": "60%",
    "savings_amount": "Saving RM30.00",
    "units_sold": 50,
    "rating_score": 5.0,
    "review_count": 13,
    "shop_name": "Life items",
    "shop_id": "7494516014240729046",
    "free_shipping": false,
    "product_url": "https://shop.tiktok.com/my/pdp/1734944123625244630",
    "image_url": "https://p16-oec-va.ibyteimg.com/tos-maliva-i-o3syd03w52-us/13ebee5d10e944d184eb65dad464c14f~tplv-o3syd03w52-crop-webp:800:800.webp?dr=15592&t=555f072d&ps=933b5bde&shp=8dbd94bf&shcp=d741f1be&idc=my&from=2378011839",
    "source": "WIRETAP"
  },
  {
    "product_id": "1733591779862939179",
    "title": "Hiasan rumah, papan tanda aluminium bulat gaya vintaj, reka bentuk botol minuman keras hiasan retro, seni dinding, untuk rumah, garaj, ruang makan, kafe, 1 keping",
    "sale_price_rm": "19.29",
    "original_price_rm": "35.49",
    "discount_percentage": "46%",
    "savings_amount": "Saving RM16.20",
    "units_sold": 62,
    "rating_score": 5.0,
    "review_count": 1,
    "shop_name": "XITU ART",
    "shop_id": "8651223193707644459",
    "free_shipping": false,
    "product_url": "https://shop.tiktok.com/my/pdp/hiasan-dinding-aluminium-bulat-gaya-vintaj-reka-bentuk-retro/1733591779862939179",
    "image_url": "https://p16-oec-va.ibyteimg.com/tos-maliva-i-o3syd03w52-us/4b458fbbc5f24c359c9554b8031f8b8a~tplv-o3syd03w52-crop-webp:800:800.webp?dr=15592&t=555f072d&ps=933b5bde&shp=8dbd94bf&shcp=d741f1be&idc=my&from=2378011839",
    "source": "WIRETAP"
  },
  {
    "product_id": "1729586645167998433",
    "title": "{Cerek Jag Potong 2L} [C] 2L Auto Off Stainless Steel Kettle Electric Automatic Jug Pemanas Serbaguna water heater",
    "sale_price_rm": "25.28",
    "original_price_rm": "0.00",
    "discount_percentage": "",
    "savings_amount": "",
    "units_sold": 1472,
    "rating_score": 3.6,
    "review_count": 69,
    "shop_name": "Colore",
    "shop_id": "7495151412876184033",
    "free_shipping": false,
    "product_url": "https://shop.tiktok.com/my/pdp/ketil-elektrik-2l-anti-karat-dengan-auto-mati-pengawal-suhu/1729586645167998433",
    "image_url": "https://p16-oec-sg.ibyteimg.com/tos-alisg-i-aphluv4xwc-sg/deeb7c12d2fa4879a19bec3ac7a7a8ea~tplv-aphluv4xwc-crop-webp:1080:1080.webp?dr=15592&t=555f072d&ps=933b5bde&shp=8dbd94bf&shcp=d741f1be&idc=my&from=2378011839",
    "source": "WIRETAP"
  },
  {
    "product_id": "1730274347742299943",
    "title": "NEO HAIR LOTION SPRAY NEW ARRIVAL MALAYSIA",
    "sale_price_rm": "113.4",
    "original_price_rm": "135",
    "discount_percentage": "16%",
    "savings_amount": "Saving RM21.60",
    "units_sold": 17741,
    "rating_score": 4.6,
    "review_count": 1041,
    "shop_name": "BAZAR SADAI 2",
    "shop_id": "7495165934034258727",
    "free_shipping": false,
    "product_url": "https://shop.tiktok.com/my/pdp/neo-hair-lotion-spray-baru-tiba-di-malaysia-untuk-rambut-sihat/1730274347742299943",
    "image_url": "https://p16-oec-sg.ibyteimg.com/tos-alisg-i-aphluv4xwc-sg/0e85abc7a1a54bd78e7fa0aae6ac2b4a~tplv-aphluv4xwc-crop-webp:800:800.webp?dr=15592&t=555f072d&ps=933b5bde&shp=8dbd94bf&shcp=d741f1be&idc=my&from=2378011839",
    "source": "WIRETAP"
  },
  {
    "product_id": "1729610574388954434",
    "title": "Apple AirTag - Pelacak Peranti dengan Teknologi Ultra Wideband",
    "sale_price_rm": "88",
    "original_price_rm": "139",
    "discount_percentage": "37%",
    "savings_amount": "Saving RM51.00",
    "units_sold": 3823,
    "rating_score": 4.9,
    "review_count": 313,
    "shop_name": "Switch Official Store",
    "shop_id": "7495695480208656706",
    "free_shipping": false,
    "product_url": "https://shop.tiktok.com/my/pdp/apple-airtag-pelacak-peranti-dengan-ultra-wideband-suara-binaan/1729610574388954434",
    "image_url": "https://p16-oec-sg.ibyteimg.com/tos-alisg-i-aphluv4xwc-sg/3a5ad09f33064e98bb684f97814faeb5~tplv-aphluv4xwc-crop-webp:800:800.webp?dr=15592&t=555f072d&ps=933b5bde&shp=8dbd94bf&shcp=d741f1be&idc=my&from=2378011839",
    "source": "WIRETAP"
  },
  {
    "product_id": "1729601285233870362",
    "title": "JOVEN SL30E SL30IP Instant Water Heater With DC Pump ELBA  Inverter Silent DC Pump Water Heater Shower Light Green Black White Rain Shower Set FREE Bidet Set paip mandi shower shower tandas",
    "sale_price_rm": "234",
    "original_price_rm": "399",
    "discount_percentage": "41%",
    "savings_amount": "Saving RM165.00",
    "units_sold": 1188,
    "rating_score": 4.7,
    "review_count": 185,
    "shop_name": "SINKIMALL",
    "shop_id": "7495168313305434650",
    "free_shipping": true,
    "product_url": "https://shop.tiktok.com/my/pdp/pemanas-air-joven-sl30e-dc-pump-set-pancuran-hujan-gratis-bidet/1729601285233870362",
    "image_url": "https://p16-oec-sg.ibyteimg.com/tos-alisg-i-aphluv4xwc-sg/f514c53faa0540078f855eb0f41e3b29~tplv-aphluv4xwc-crop-webp:1200:1200.webp?dr=15592&t=555f072d&ps=933b5bde&shp=8dbd94bf&shcp=d741f1be&idc=my&from=2378011839",
    "source": "WIRETAP"
  },
  {
    "product_id": "1736023387501397451",
    "title": "Zinc Alloy Hand Warmer Reusable Portable Fuel Heater Fuel Hand Warmers Heater for Outdoor Hunting Camping Fishing",
    "sale_price_rm": "32.54",
    "original_price_rm": "33.04",
    "discount_percentage": "2%",
    "savings_amount": "Saving RM0.50",
    "units_sold": 0,
    "rating_score": 0.0,
    "review_count": 0,
    "shop_name": "Winnereco Flagships",
    "shop_id": "8664788840465270219",
    "free_shipping": false,
    "product_url": "https://shop.tiktok.com/my/pdp/1736023387501397451",
    "image_url": "https://p16-oec-sg.ibyteimg.com/tos-alisg-i-aphluv4xwc-sg/ff632d9e471f4b16a7dd05e429496193~tplv-aphluv4xwc-crop-webp:1001:1001.webp?dr=15592&t=555f072d&ps=933b5bde&shp=8dbd94bf&shcp=d741f1be&idc=my&from=2378011839",
    "source": "WIRETAP"
  },
  {
    "product_id": "1732008118115861801",
    "title": "AED Trainer with Remote Control Dual Language Bahasa Malaysia and English",
    "sale_price_rm": "935",
    "original_price_rm": "0.00",
    "discount_percentage": "",
    "savings_amount": "",
    "units_sold": 1,
    "rating_score": 0.0,
    "review_count": 0,
    "shop_name": "First Aid Store",
    "shop_id": "7494963954511546665",
    "free_shipping": false,
    "product_url": "https://shop.tiktok.com/my/pdp/pengawal-remotik-dua-bahasa-untuk-latihan-aed-model-xft-120c/1732008118115861801",
    "image_url": "https://p16-oec-sg.ibyteimg.com/tos-alisg-i-aphluv4xwc-sg/e24715d1b22746db974f2450f7a7812a~tplv-aphluv4xwc-crop-webp:2500:2500.webp?dr=15592&t=555f072d&ps=933b5bde&shp=8dbd94bf&shcp=d741f1be&idc=my&from=2378011839",
    "source": "WIRETAP"
  },
  {
    "product_id": "1734924917240924105",
    "title": "Lego The Movie 2 Videogame USED GAMES PHYSICAL",
    "sale_price_rm": "90",
    "original_price_rm": "0.00",
    "discount_percentage": "",
    "savings_amount": "",
    "units_sold": 1,
    "rating_score": 0.0,
    "review_count": 0,
    "shop_name": "GamingSky",
    "shop_id": "7494955284461816777",
    "free_shipping": false,
    "product_url": "https://shop.tiktok.com/my/pdp/1734924917240924105",
    "image_url": "https://p16-oec-sg.ibyteimg.com/tos-alisg-i-aphluv4xwc-sg/2d2fb56e9df040bc9da3f75db0f050df~tplv-aphluv4xwc-crop-webp:1179:1179.webp?dr=15592&t=555f072d&ps=933b5bde&shp=8dbd94bf&shcp=d741f1be&idc=my&from=2378011839",
    "source": "WIRETAP"
  },
  {
    "product_id": "1731478034416109220",
    "title": "Piano elektronik, BETSY B151， Boleh dilipat, 61 kekunci, sesuai untuk pemula kanak-kanak, hadiah",
    "sale_price_rm": "159",
    "original_price_rm": "269",
    "discount_percentage": "41%",
    "savings_amount": "Saving RM110.00",
    "units_sold": 14266,
    "rating_score": 4.8,
    "review_count": 5303,
    "shop_name": "BETSY MUSICAL INSTRUMENT",
    "shop_id": "8649263419419100836",
    "free_shipping": false,
    "product_url": "https://shop.tiktok.com/my/pdp/piano-elektronik-lipat-betsy-b151-61-kekunci-mudah-alih/1731478034416109220",
    "image_url": "https://p16-oec-sg.ibyteimg.com/tos-alisg-i-aphluv4xwc-sg/c71f7824310a4ccfb89f2ced9ac291bc~tplv-aphluv4xwc-crop-webp:2000:2000.webp?dr=15592&t=555f072d&ps=933b5bde&shp=8dbd94bf&shcp=d741f1be&idc=my&from=2378011839",
    "source": "WIRETAP"
  },
  {
    "product_id": "1729851339093542529",
    "title": "SB200 Basikal Senam Indoor Basikal Kayuh Senaman Spinning Bike Exercise Dengan Tahanan Tidak Terhad LCD Display Stabil Selamat & Nyaman Sesuai Untuk Pejabat Keluarga Rumah Program Pelangsingan Keselesaan & Keselamatan Tinggi",
    "sale_price_rm": "205.99",
    "original_price_rm": "599.99",
    "discount_percentage": "66%",
    "savings_amount": "Saving RM394.00",
    "units_sold": 672,
    "rating_score": 4.8,
    "review_count": 179,
    "shop_name": "emascare.os",
    "shop_id": "7495900798124526209",
    "free_shipping": false,
    "product_url": "https://shop.tiktok.com/my/pdp/sb200-basikal-senam-indoor-paparan-lcd-tahanan-tak-terhad/1729851339093542529",
    "image_url": "https://p16-oec-sg.ibyteimg.com/tos-alisg-i-aphluv4xwc-sg/d49a4feaf469461191ab0fc509c7cf2e~tplv-aphluv4xwc-crop-webp:1024:1024.webp?dr=15592&t=555f072d&ps=933b5bde&shp=8dbd94bf&shcp=d741f1be&idc=my&from=2378011839",
    "source": "WIRETAP"
  },
  {
    "product_id": "1736268180664321296",
    "title": "Jualan panas [TERMURAH] PERMAINAN PC RIVALS",
    "sale_price_rm": "46.12",
    "original_price_rm": "95.6",
    "discount_percentage": "52%",
    "savings_amount": "Saving RM49.48",
    "units_sold": 0,
    "rating_score": 0.0,
    "review_count": 0,
    "shop_name": "LNFINITY",
    "shop_id": "7494736820112164112",
    "free_shipping": false,
    "product_url": "https://shop.tiktok.com/my/pdp/1736268180664321296",
    "image_url": "https://p16-oec-sg.ibyteimg.com/tos-alisg-i-aphluv4xwc-sg/548d9c595dde45a4a41d09f2ed2777e4~tplv-aphluv4xwc-crop-webp:1024:1024.webp?dr=15592&t=555f072d&ps=933b5bde&shp=8dbd94bf&shcp=d741f1be&idc=my&from=2378011839",
    "source": "WIRETAP"
  },
  {
    "product_id": "1734407265400816769",
    "title": "Pemanas Tangan Magnet Mini Rentas Sempadan Boleh Dicas semula Hadiah Mudah Alih Split Pegang Tangan Artifak Hadiah Musim Sejuk",
    "sale_price_rm": "22.3",
    "original_price_rm": "0.00",
    "discount_percentage": "",
    "savings_amount": "",
    "units_sold": 0,
    "rating_score": 0.0,
    "review_count": 0,
    "shop_name": "Rolando616514",
    "shop_id": "8659380310464496769",
    "free_shipping": false,
    "product_url": "https://shop.tiktok.com/my/pdp/pemanas-tangan-magnet-mini-usb-kapasiti-2000mah-4000mah/1734407265400816769",
    "image_url": "https://p16-oec-va.ibyteimg.com/tos-maliva-i-o3syd03w52-us/f585b1ff477e45d0a48705b3fa9983b6~tplv-o3syd03w52-crop-webp:800:800.webp?dr=15592&t=555f072d&ps=933b5bde&shp=8dbd94bf&shcp=d741f1be&idc=my&from=2378011839",
    "source": "WIRETAP"
  },
  {
    "product_id": "1729478941945398338",
    "title": "HAFANA BARLI TANPA GULA PUTIH, EXTRACT KURMA DELIMA MORINGGA GYMNEMA, BUAH MONK",
    "sale_price_rm": "11.99",
    "original_price_rm": "25",
    "discount_percentage": "52%",
    "savings_amount": "Saving RM13.01",
    "units_sold": 247289,
    "rating_score": 4.8,
    "review_count": 30318,
    "shop_name": "hafana marketing",
    "shop_id": "7494727130607945794",
    "free_shipping": false,
    "product_url": "https://shop.tiktok.com/my/pdp/serbuk-barli-tiada-gula-minuman-instant-delima-moringga-12-sachet/1729478941945398338",
    "image_url": "https://p16-oec-sg.ibyteimg.com/tos-alisg-i-aphluv4xwc-sg/7e9f1dbddb3e4e52a3ad58979f955eae~tplv-aphluv4xwc-crop-webp:1000:1000.webp?dr=15592&t=555f072d&ps=933b5bde&shp=8dbd94bf&shcp=d741f1be&idc=my&from=2378011839",
    "source": "WIRETAP"
  }
]